frasa/__init__.py
frasa/base.py
frasa/update.py
frasa/azlyrics/__init__.py
frasa/azlyrics/azlyrics.py
frasa/azlyrics/jaro.py
frasa/azlyrics/requester.py
frasa/azlyrics/tools.py
frasa/datasets/__init__.py
frasa/datasets/corpus/__init__.py
frasa/datasets/corpus/bahasa/__init__.py
frasa/datasets/corpus/indonesia/__init__.py
frasa/datasets/corpus/indonesia/stopword.txt
frasa/datasets/corpus/indonesia/lemma/clitics.txt
frasa/datasets/corpus/indonesia/lemma/dict.json
frasa/datasets/corpus/indonesia/lemma/root.txt
frasa/datasets/corpus/sensor/__init__.py
frasa/datasets/corpus/sensor/alphabetic_unicode.json
frasa/datasets/corpus/sensor/sensor-aturan.csv
frasa/datasets/corpus/sensor/sensor-kata.csv
frasa/datasets/corpus/sensor/sensor-pengganti.csv
frasa/datasets/corpus/tweets/__init__.py
frasa/datasets/models/__init__.py
frasa/datasets/models/frasa-gender.pickle
frasa/datasets/models/nusax/aceh_model.pkl
frasa/datasets/models/nusax/aceh_vectorizer.pkl
frasa/datasets/models/nusax/bali_model.pkl
frasa/datasets/models/nusax/bali_vectorizer.pkl
frasa/datasets/models/nusax/banjar_model.pkl
frasa/datasets/models/nusax/banjar_vectorizer.pkl
frasa/datasets/models/nusax/batak_model.pkl
frasa/datasets/models/nusax/batak_vectorizer.pkl
frasa/datasets/models/nusax/bugis_model.pkl
frasa/datasets/models/nusax/bugis_vectorizer.pkl
frasa/datasets/models/nusax/indo_model.pkl
frasa/datasets/models/nusax/indo_vectorizer.pkl
frasa/datasets/models/nusax/jawa_model.pkl
frasa/datasets/models/nusax/jawa_vectorizer.pkl
frasa/datasets/models/nusax/madura_model.pkl
frasa/datasets/models/nusax/madura_vectorizer.pkl
frasa/datasets/models/nusax/minang_model.pkl
frasa/datasets/models/nusax/minang_vectorizer.pkl
frasa/datasets/models/nusax/ngaju_model.pkl
frasa/datasets/models/nusax/ngaju_vectorizer.pkl
frasa/datasets/models/nusax/sunda_model.pkl
frasa/datasets/models/nusax/sunda_vectorizer.pkl
frasa/deteksi/__init__.py
frasa/deteksi/bahasa/__init__.py
frasa/deteksi/bahasa/data/__init__.py
frasa-0.1.58.dist-info/LICENSE
frasa-0.1.58.dist-info/METADATA
frasa-0.1.58.dist-info/WHEEL
frasa-0.1.58.dist-info/top_level.txt
frasa-0.1.58.dist-info/RECORD
