Metadata-Version: 2.1
Name: frasa
Version: 0.1.58
Summary: Koleksi NLP Pribadi untuk Bahasa Indonesia.
Home-page: https://github.com/novay/frasa
Author: Novianto Rahmadi
Author-email: novay@btekno.id
License: MIT
Classifier: Intended Audience :: Developers
Classifier: License :: OSI Approved :: MIT License
Classifier: Programming Language :: Python
Classifier: Programming Language :: Python :: 3
Classifier: Programming Language :: Python :: 3.6
Classifier: Programming Language :: Python :: 3.7
Classifier: Programming Language :: Python :: 3.8
Classifier: Programming Language :: Python :: 3.9
Classifier: Operating System :: OS Independent
License-File: LICENSE
Requires-Dist: requests
Requires-Dist: bs4
